async_decorator/LICENSE
async_decorator/__init__.py
async_decorator/_version.py
async_decorator/core/__init__.py
async_decorator/core/decorators.py
async_decorator/core/manager.py
async_decorator/core/types.py
async_decorator/scripts/release.py
async_decorator/utils/__init__.py
async_decorator/utils/exceptions.py
async_decorator/utils/validators.py
async_decorator-0.1.1.dist-info/METADATA
async_decorator-0.1.1.dist-info/WHEEL
async_decorator-0.1.1.dist-info/top_level.txt
async_decorator-0.1.1.dist-info/RECORD
