Metadata-Version: 2.1
Name: async-decorator
Version: 0.1.1
Summary: A flexible async/sync execution library with dedicated thread pools
Home-page: https://github.com/FadsII/async-decorator
Author: FadsII
Author-email: FadsII <594604366@qq.com>
License: MIT
Project-URL: Homepage, https://github.com/FadsII/async-decorator
Project-URL: Documentation, https://github.com/FadsII/async-decorator#readme
Project-URL: Repository, https://github.com/FadsII/async-decorator
Project-URL: Issues, https://github.com/FadsII/async-decorator/issues
Keywords: async,threading,executor,decorator
Classifier: Development Status :: 4 - Beta
Classifier: Intended Audience :: Developers
Classifier: License :: OSI Approved :: MIT License
Classifier: Operating System :: OS Independent
Classifier: Programming Language :: Python :: 3
Classifier: Programming Language :: Python :: 3.8
Classifier: Programming Language :: Python :: 3.9
Classifier: Programming Language :: Python :: 3.10
Classifier: Programming Language :: Python :: 3.11
Classifier: Programming Language :: Python :: 3.12
Classifier: Topic :: Software Development :: Libraries :: Python Modules
Requires-Python: >=3.8
Provides-Extra: dev
Requires-Dist: pytest>=6.0; extra == "dev"
Requires-Dist: pytest-asyncio>=0.15; extra == "dev"
Requires-Dist: black>=21.0; extra == "dev"
Requires-Dist: isort>=5.0; extra == "dev"
Requires-Dist: mypy>=0.900; extra == "dev"
Requires-Dist: twine>=4.0; extra == "dev"
